AUTHORS.rst
LICENSE
MANIFEST.in
README.rst
setup.py
django_thumbs/__init__.py
django_thumbs/settings.py
django_thumbs.egg-info/PKG-INFO
django_thumbs.egg-info/SOURCES.txt
django_thumbs.egg-info/dependency_links.txt
django_thumbs.egg-info/top_level.txt
django_thumbs/db/__init__.py
django_thumbs/db/models.py