Metadata-Version: 1.1
Name: django-thumbs
Version: 0.4
Summary: Django-Thumbs is the easiest way to create thumbnails for your images with Django. Works with any StorageBackend.
Home-page: https://github.com/skitoo/django-thumbs
Author: Antonio Melé
Author-email: antonio.mele@gmail.com
License: New BSD License
Keywords: django thumbs image
Platform: OS Independent
Classifier: Development Status :: 4 - Beta
Classifier: Environment :: Web Environment
Classifier: Framework :: Django
Classifier: Intended Audience :: Developers
Classifier: License :: OSI Approved :: BSD License
Classifier: Operating System :: OS Independent
Classifier: Programming Language :: Python
Classifier: Programming Language :: Python :: 2.5
Classifier: Programming Language :: Python :: 2.6
Classifier: Programming Language :: Python :: 2.7
Classifier: Topic :: Internet :: WWW/HTTP :: Dynamic Content
Classifier: Topic :: Software Development
Classifier: Topic :: Software Development :: Libraries :: Application Frameworks
